[
    {
        "client_msg_id": "464f6749-3776-4cec-9ee8-b5ac69cd8b32",
        "type": "message",
        "text": "<!channel> just letting y'all know that Mr peck is donating some extra time tomorrow for people to come in and work on their robot, there will be a meeting tomorrow till 4pm",
        "user": "U022WGTQ602",
        "ts": "1651708629.758229",
        "blocks": [
            {
                "type": "rich_text",
                "block_id": "tN2fI",
                "elements": [
                    {
                        "type": "rich_text_section",
                        "elements": [
                            {
                                "type": "broadcast",
                                "range": "channel"
                            },
                            {
                                "type": "text",
                                "text": " just letting y'all know that Mr peck is donating some extra time tomorrow for people to come in and work on their robot, there will be a meeting tomorrow till 4pm"
                            }
                        ]
                    }
                ]
            }
        ],
        "team": "T010YRDV4KB",
        "user_team": "T010YRDV4KB",
        "source_team": "T010YRDV4KB",
        "user_profile": {
            "avatar_hash": "747c846ded5f",
            "image_72": "https:\/\/avatars.slack-edge.com\/2021-05-24\/2098572895346_747c846ded5f6d63f228_72.png",
            "first_name": "",
            "real_name": "Camden Harris",
            "display_name": "Camden Harris",
            "team": "T010YRDV4KB",
            "name": "cam.har000",
            "is_restricted": false,
            "is_ultra_restricted": false
        }
    },
    {
        "client_msg_id": "45e9d69e-c099-41d7-9d38-75bab4413a8f",
        "type": "message",
        "text": "does everyone have a robot (that can compete) at the moment?",
        "user": "U01CZUZA4F3",
        "ts": "1651718694.289049",
        "blocks": [
            {
                "type": "rich_text",
                "block_id": "cB9",
                "elements": [
                    {
                        "type": "rich_text_section",
                        "elements": [
                            {
                                "type": "text",
                                "text": "does everyone have a robot (that can compete) at the moment?"
                            }
                        ]
                    }
                ]
            }
        ],
        "team": "T010YRDV4KB",
        "user_team": "T010YRDV4KB",
        "source_team": "T010YRDV4KB",
        "user_profile": {
            "avatar_hash": "2340daecb5c9",
            "image_72": "https:\/\/avatars.slack-edge.com\/2020-10-14\/1429586810659_2340daecb5c97157acec_72.png",
            "first_name": "Derek",
            "real_name": "Derek Nguyen",
            "display_name": "Derek Nguyen",
            "team": "T010YRDV4KB",
            "name": "derek.nguyen1028",
            "is_restricted": false,
            "is_ultra_restricted": false
        }
    },
    {
        "client_msg_id": "7f93fa96-1cd7-48ea-b89e-e7491880abd7",
        "type": "message",
        "text": "nope, not one lmao",
        "user": "U022WGTQ602",
        "ts": "1651718715.060199",
        "blocks": [
            {
                "type": "rich_text",
                "block_id": "a8W",
                "elements": [
                    {
                        "type": "rich_text_section",
                        "elements": [
                            {
                                "type": "text",
                                "text": "nope, not one lmao"
                            }
                        ]
                    }
                ]
            }
        ],
        "team": "T010YRDV4KB",
        "user_team": "T010YRDV4KB",
        "source_team": "T010YRDV4KB",
        "user_profile": {
            "avatar_hash": "747c846ded5f",
            "image_72": "https:\/\/avatars.slack-edge.com\/2021-05-24\/2098572895346_747c846ded5f6d63f228_72.png",
            "first_name": "",
            "real_name": "Camden Harris",
            "display_name": "Camden Harris",
            "team": "T010YRDV4KB",
            "name": "cam.har000",
            "is_restricted": false,
            "is_ultra_restricted": false
        }
    },
    {
        "client_msg_id": "a855fe4d-8016-48ae-a379-1bb24c8d750b",
        "type": "message",
        "text": "oh LMAO",
        "user": "U01CZUZA4F3",
        "ts": "1651719452.260779",
        "blocks": [
            {
                "type": "rich_text",
                "block_id": "UW0l",
                "elements": [
                    {
                        "type": "rich_text_section",
                        "elements": [
                            {
                                "type": "text",
                                "text": "oh LMAO"
                            }
                        ]
                    }
                ]
            }
        ],
        "team": "T010YRDV4KB",
        "user_team": "T010YRDV4KB",
        "source_team": "T010YRDV4KB",
        "user_profile": {
            "avatar_hash": "2340daecb5c9",
            "image_72": "https:\/\/avatars.slack-edge.com\/2020-10-14\/1429586810659_2340daecb5c97157acec_72.png",
            "first_name": "Derek",
            "real_name": "Derek Nguyen",
            "display_name": "Derek Nguyen",
            "team": "T010YRDV4KB",
            "name": "derek.nguyen1028",
            "is_restricted": false,
            "is_ultra_restricted": false
        }
    },
    {
        "client_msg_id": "d37d22fc-702e-42d9-a320-7d7adc894b16",
        "type": "message",
        "text": "fat L to all the teams so glad im not part of any of them :sunglasses:",
        "user": "U01CZUZA4F3",
        "ts": "1651719489.082739",
        "blocks": [
            {
                "type": "rich_text",
                "block_id": "O7Wt",
                "elements": [
                    {
                        "type": "rich_text_section",
                        "elements": [
                            {
                                "type": "text",
                                "text": "fat L to all the teams so glad im not part of any of them "
                            },
                            {
                                "type": "emoji",
                                "name": "sunglasses",
                                "unicode": "1f60e"
                            }
                        ]
                    }
                ]
            }
        ],
        "team": "T010YRDV4KB",
        "user_team": "T010YRDV4KB",
        "source_team": "T010YRDV4KB",
        "user_profile": {
            "avatar_hash": "2340daecb5c9",
            "image_72": "https:\/\/avatars.slack-edge.com\/2020-10-14\/1429586810659_2340daecb5c97157acec_72.png",
            "first_name": "Derek",
            "real_name": "Derek Nguyen",
            "display_name": "Derek Nguyen",
            "team": "T010YRDV4KB",
            "name": "derek.nguyen1028",
            "is_restricted": false,
            "is_ultra_restricted": false
        }
    },
    {
        "client_msg_id": "a4096a7d-68ee-4829-b395-af8373320184",
        "type": "message",
        "text": "Max and Isaac's team could probably park during auto given a day to program a nd fix their bevel gears",
        "user": "U0118UR0J72",
        "ts": "1651725748.720389",
        "blocks": [
            {
                "type": "rich_text",
                "block_id": "vy9qf",
                "elements": [
                    {
                        "type": "rich_text_section",
                        "elements": [
                            {
                                "type": "text",
                                "text": "Max and Isaac's team could probably park during auto given a day to program a nd fix their bevel gears"
                            }
                        ]
                    }
                ]
            }
        ],
        "team": "T010YRDV4KB",
        "user_team": "T010YRDV4KB",
        "source_team": "T010YRDV4KB",
        "user_profile": {
            "avatar_hash": "8341efb67434",
            "image_72": "https:\/\/avatars.slack-edge.com\/2021-03-31\/1918276099570_8341efb67434b5b5386a_72.png",
            "first_name": "Sam",
            "real_name": "Sam DePoule",
            "display_name": "Sam DePoule",
            "team": "T010YRDV4KB",
            "name": "samdepoule",
            "is_restricted": false,
            "is_ultra_restricted": false
        }
    },
    {
        "client_msg_id": "251f9611-2922-4fc1-abb7-5d9ddc1405f5",
        "type": "message",
        "text": "oh aight, didn't realize they were that far along, that's good",
        "user": "U022WGTQ602",
        "ts": "1651725816.625359",
        "blocks": [
            {
                "type": "rich_text",
                "block_id": "0F04v",
                "elements": [
                    {
                        "type": "rich_text_section",
                        "elements": [
                            {
                                "type": "text",
                                "text": "oh aight, didn't realize they were that far along, that's good"
                            }
                        ]
                    }
                ]
            }
        ],
        "team": "T010YRDV4KB",
        "user_team": "T010YRDV4KB",
        "source_team": "T010YRDV4KB",
        "user_profile": {
            "avatar_hash": "747c846ded5f",
            "image_72": "https:\/\/avatars.slack-edge.com\/2021-05-24\/2098572895346_747c846ded5f6d63f228_72.png",
            "first_name": "",
            "real_name": "Camden Harris",
            "display_name": "Camden Harris",
            "team": "T010YRDV4KB",
            "name": "cam.har000",
            "is_restricted": false,
            "is_ultra_restricted": false
        }
    },
    {
        "client_msg_id": "0aaf6482-c4bd-4446-9454-bd16c8d10ae9",
        "type": "message",
        "text": "at least we'll have one team for comp lol",
        "user": "U022WGTQ602",
        "ts": "1651725829.397689",
        "blocks": [
            {
                "type": "rich_text",
                "block_id": "9xRoV",
                "elements": [
                    {
                        "type": "rich_text_section",
                        "elements": [
                            {
                                "type": "text",
                                "text": "at least we'll have one team for comp lol"
                            }
                        ]
                    }
                ]
            }
        ],
        "team": "T010YRDV4KB",
        "user_team": "T010YRDV4KB",
        "source_team": "T010YRDV4KB",
        "user_profile": {
            "avatar_hash": "747c846ded5f",
            "image_72": "https:\/\/avatars.slack-edge.com\/2021-05-24\/2098572895346_747c846ded5f6d63f228_72.png",
            "first_name": "",
            "real_name": "Camden Harris",
            "display_name": "Camden Harris",
            "team": "T010YRDV4KB",
            "name": "cam.har000",
            "is_restricted": false,
            "is_ultra_restricted": false
        }
    },
    {
        "client_msg_id": "4cc6c685-d72a-4f7e-83e0-ae1766132546",
        "type": "message",
        "text": ":skull: they boutta win with no competition",
        "user": "U01CZUZA4F3",
        "ts": "1651725854.733089",
        "blocks": [
            {
                "type": "rich_text",
                "block_id": "kq0",
                "elements": [
                    {
                        "type": "rich_text_section",
                        "elements": [
                            {
                                "type": "emoji",
                                "name": "skull",
                                "unicode": "1f480"
                            },
                            {
                                "type": "text",
                                "text": " they boutta win with no competition"
                            }
                        ]
                    }
                ]
            }
        ],
        "team": "T010YRDV4KB",
        "user_team": "T010YRDV4KB",
        "source_team": "T010YRDV4KB",
        "user_profile": {
            "avatar_hash": "2340daecb5c9",
            "image_72": "https:\/\/avatars.slack-edge.com\/2020-10-14\/1429586810659_2340daecb5c97157acec_72.png",
            "first_name": "Derek",
            "real_name": "Derek Nguyen",
            "display_name": "Derek Nguyen",
            "team": "T010YRDV4KB",
            "name": "derek.nguyen1028",
            "is_restricted": false,
            "is_ultra_restricted": false
        }
    },
    {
        "client_msg_id": "aaa5b554-b65f-4e77-9fff-300e1ca669e1",
        "type": "message",
        "text": "that means they automatically win",
        "user": "U0118UR0J72",
        "ts": "1651725857.497769",
        "blocks": [
            {
                "type": "rich_text",
                "block_id": "V7rV",
                "elements": [
                    {
                        "type": "rich_text_section",
                        "elements": [
                            {
                                "type": "text",
                                "text": "that means they automatically win"
                            }
                        ]
                    }
                ]
            }
        ],
        "team": "T010YRDV4KB",
        "user_team": "T010YRDV4KB",
        "source_team": "T010YRDV4KB",
        "user_profile": {
            "avatar_hash": "8341efb67434",
            "image_72": "https:\/\/avatars.slack-edge.com\/2021-03-31\/1918276099570_8341efb67434b5b5386a_72.png",
            "first_name": "Sam",
            "real_name": "Sam DePoule",
            "display_name": "Sam DePoule",
            "team": "T010YRDV4KB",
            "name": "samdepoule",
            "is_restricted": false,
            "is_ultra_restricted": false
        }
    },
    {
        "client_msg_id": "3f0c8b18-aefc-4411-ba29-2ff108f54886",
        "type": "message",
        "text": "unless their alliance gets a ton of negative points and they tie",
        "user": "U0118UR0J72",
        "ts": "1651725872.927739",
        "blocks": [
            {
                "type": "rich_text",
                "block_id": "b+SQ",
                "elements": [
                    {
                        "type": "rich_text_section",
                        "elements": [
                            {
                                "type": "text",
                                "text": "unless their alliance gets a ton of negative points and they tie"
                            }
                        ]
                    }
                ]
            }
        ],
        "team": "T010YRDV4KB",
        "user_team": "T010YRDV4KB",
        "source_team": "T010YRDV4KB",
        "user_profile": {
            "avatar_hash": "8341efb67434",
            "image_72": "https:\/\/avatars.slack-edge.com\/2021-03-31\/1918276099570_8341efb67434b5b5386a_72.png",
            "first_name": "Sam",
            "real_name": "Sam DePoule",
            "display_name": "Sam DePoule",
            "team": "T010YRDV4KB",
            "name": "samdepoule",
            "is_restricted": false,
            "is_ultra_restricted": false
        }
    },
    {
        "client_msg_id": "f487d563-7da3-4f00-920a-80a0bce5b943",
        "type": "message",
        "text": "better than a guaranteed 4 way tie",
        "user": "U022WGTQ602",
        "ts": "1651725903.619929",
        "blocks": [
            {
                "type": "rich_text",
                "block_id": "haRc",
                "elements": [
                    {
                        "type": "rich_text_section",
                        "elements": [
                            {
                                "type": "text",
                                "text": "better than a guaranteed 4 way tie"
                            }
                        ]
                    }
                ]
            }
        ],
        "team": "T010YRDV4KB",
        "user_team": "T010YRDV4KB",
        "source_team": "T010YRDV4KB",
        "user_profile": {
            "avatar_hash": "747c846ded5f",
            "image_72": "https:\/\/avatars.slack-edge.com\/2021-05-24\/2098572895346_747c846ded5f6d63f228_72.png",
            "first_name": "",
            "real_name": "Camden Harris",
            "display_name": "Camden Harris",
            "team": "T010YRDV4KB",
            "name": "cam.har000",
            "is_restricted": false,
            "is_ultra_restricted": false
        }
    },
    {
        "client_msg_id": "de7c14c7-d004-4dad-b3d6-42065e073103",
        "type": "message",
        "text": "lol",
        "user": "U0118UR0J72",
        "ts": "1651725911.458789",
        "blocks": [
            {
                "type": "rich_text",
                "block_id": "xHv9",
                "elements": [
                    {
                        "type": "rich_text_section",
                        "elements": [
                            {
                                "type": "text",
                                "text": "lol"
                            }
                        ]
                    }
                ]
            }
        ],
        "team": "T010YRDV4KB",
        "user_team": "T010YRDV4KB",
        "source_team": "T010YRDV4KB",
        "user_profile": {
            "avatar_hash": "8341efb67434",
            "image_72": "https:\/\/avatars.slack-edge.com\/2021-03-31\/1918276099570_8341efb67434b5b5386a_72.png",
            "first_name": "Sam",
            "real_name": "Sam DePoule",
            "display_name": "Sam DePoule",
            "team": "T010YRDV4KB",
            "name": "samdepoule",
            "is_restricted": false,
            "is_ultra_restricted": false
        }
    },
    {
        "client_msg_id": "17033244-2e4d-426d-8ca5-dba90f562b63",
        "type": "message",
        "text": "so true",
        "user": "U01CZUZA4F3",
        "ts": "1651725931.000609",
        "blocks": [
            {
                "type": "rich_text",
                "block_id": "HI+",
                "elements": [
                    {
                        "type": "rich_text_section",
                        "elements": [
                            {
                                "type": "text",
                                "text": "so true"
                            }
                        ]
                    }
                ]
            }
        ],
        "team": "T010YRDV4KB",
        "user_team": "T010YRDV4KB",
        "source_team": "T010YRDV4KB",
        "user_profile": {
            "avatar_hash": "2340daecb5c9",
            "image_72": "https:\/\/avatars.slack-edge.com\/2020-10-14\/1429586810659_2340daecb5c97157acec_72.png",
            "first_name": "Derek",
            "real_name": "Derek Nguyen",
            "display_name": "Derek Nguyen",
            "team": "T010YRDV4KB",
            "name": "derek.nguyen1028",
            "is_restricted": false,
            "is_ultra_restricted": false
        }
    },
    {
        "client_msg_id": "6132a22d-70d9-4717-b5a2-3fd7a74997a2",
        "type": "message",
        "text": "is there a reward for the winner tho",
        "user": "U01CZUZA4F3",
        "ts": "1651725935.583239",
        "blocks": [
            {
                "type": "rich_text",
                "block_id": "qH2S",
                "elements": [
                    {
                        "type": "rich_text_section",
                        "elements": [
                            {
                                "type": "text",
                                "text": "is there a reward for the winner tho"
                            }
                        ]
                    }
                ]
            }
        ],
        "team": "T010YRDV4KB",
        "user_team": "T010YRDV4KB",
        "source_team": "T010YRDV4KB",
        "user_profile": {
            "avatar_hash": "2340daecb5c9",
            "image_72": "https:\/\/avatars.slack-edge.com\/2020-10-14\/1429586810659_2340daecb5c97157acec_72.png",
            "first_name": "Derek",
            "real_name": "Derek Nguyen",
            "display_name": "Derek Nguyen",
            "team": "T010YRDV4KB",
            "name": "derek.nguyen1028",
            "is_restricted": false,
            "is_ultra_restricted": false
        }
    },
    {
        "client_msg_id": "227503f1-9a04-4886-848b-1271fdb57cfc",
        "type": "message",
        "text": "the candy in the closet?",
        "user": "U0118UR0J72",
        "ts": "1651725946.797849",
        "blocks": [
            {
                "type": "rich_text",
                "block_id": "wFe",
                "elements": [
                    {
                        "type": "rich_text_section",
                        "elements": [
                            {
                                "type": "text",
                                "text": "the candy in the closet?"
                            }
                        ]
                    }
                ]
            }
        ],
        "team": "T010YRDV4KB",
        "user_team": "T010YRDV4KB",
        "source_team": "T010YRDV4KB",
        "user_profile": {
            "avatar_hash": "8341efb67434",
            "image_72": "https:\/\/avatars.slack-edge.com\/2021-03-31\/1918276099570_8341efb67434b5b5386a_72.png",
            "first_name": "Sam",
            "real_name": "Sam DePoule",
            "display_name": "Sam DePoule",
            "team": "T010YRDV4KB",
            "name": "samdepoule",
            "is_restricted": false,
            "is_ultra_restricted": false
        }
    },
    {
        "client_msg_id": "a811cb1a-cedd-46b6-99de-05f54aefc91e",
        "type": "message",
        "text": "pride",
        "user": "U022WGTQ602",
        "ts": "1651725947.376969",
        "blocks": [
            {
                "type": "rich_text",
                "block_id": "Txfn3",
                "elements": [
                    {
                        "type": "rich_text_section",
                        "elements": [
                            {
                                "type": "text",
                                "text": "pride"
                            }
                        ]
                    }
                ]
            }
        ],
        "team": "T010YRDV4KB",
        "user_team": "T010YRDV4KB",
        "source_team": "T010YRDV4KB",
        "user_profile": {
            "avatar_hash": "747c846ded5f",
            "image_72": "https:\/\/avatars.slack-edge.com\/2021-05-24\/2098572895346_747c846ded5f6d63f228_72.png",
            "first_name": "",
            "real_name": "Camden Harris",
            "display_name": "Camden Harris",
            "team": "T010YRDV4KB",
            "name": "cam.har000",
            "is_restricted": false,
            "is_ultra_restricted": false
        }
    },
    {
        "client_msg_id": "328f6a82-72da-4135-a375-5fce033d66ac",
        "type": "message",
        "text": "oh my god are you referring to the expired candy conner brought",
        "user": "U01CZUZA4F3",
        "ts": "1651725967.069839",
        "blocks": [
            {
                "type": "rich_text",
                "block_id": "Pnk",
                "elements": [
                    {
                        "type": "rich_text_section",
                        "elements": [
                            {
                                "type": "text",
                                "text": "oh my god are you referring to the expired candy conner brought"
                            }
                        ]
                    }
                ]
            }
        ],
        "team": "T010YRDV4KB",
        "user_team": "T010YRDV4KB",
        "source_team": "T010YRDV4KB",
        "user_profile": {
            "avatar_hash": "2340daecb5c9",
            "image_72": "https:\/\/avatars.slack-edge.com\/2020-10-14\/1429586810659_2340daecb5c97157acec_72.png",
            "first_name": "Derek",
            "real_name": "Derek Nguyen",
            "display_name": "Derek Nguyen",
            "team": "T010YRDV4KB",
            "name": "derek.nguyen1028",
            "is_restricted": false,
            "is_ultra_restricted": false
        }
    },
    {
        "client_msg_id": "dc2ee24b-59b0-4fe4-b130-a2e847cdc9d0",
        "type": "message",
        "text": "An extra piece of candy per person on the winning team?",
        "user": "U0118UR0J72",
        "ts": "1651725967.185999",
        "blocks": [
            {
                "type": "rich_text",
                "block_id": "t\/Kt",
                "elements": [
                    {
                        "type": "rich_text_section",
                        "elements": [
                            {
                                "type": "text",
                                "text": "An extra piece of candy per person on the winning team?"
                            }
                        ]
                    }
                ]
            }
        ],
        "team": "T010YRDV4KB",
        "user_team": "T010YRDV4KB",
        "source_team": "T010YRDV4KB",
        "user_profile": {
            "avatar_hash": "8341efb67434",
            "image_72": "https:\/\/avatars.slack-edge.com\/2021-03-31\/1918276099570_8341efb67434b5b5386a_72.png",
            "first_name": "Sam",
            "real_name": "Sam DePoule",
            "display_name": "Sam DePoule",
            "team": "T010YRDV4KB",
            "name": "samdepoule",
            "is_restricted": false,
            "is_ultra_restricted": false
        },
        "thread_ts": "1651725967.185999",
        "reply_count": 2,
        "reply_users_count": 2,
        "latest_reply": "1651758834.647239",
        "reply_users": [
            "U022WGTQ602",
            "U02DWDDVAP7"
        ],
        "replies": [
            {
                "user": "U022WGTQ602",
                "ts": "1651726003.485599"
            },
            {
                "user": "U02DWDDVAP7",
                "ts": "1651758834.647239"
            }
        ],
        "is_locked": false,
        "subscribed": false
    },
    {
        "client_msg_id": "0b674323-b651-4f53-8897-2f929a2c730b",
        "type": "message",
        "text": "that sounds like a great idea",
        "user": "U01CZUZA4F3",
        "ts": "1651725983.800879",
        "blocks": [
            {
                "type": "rich_text",
                "block_id": "eVd=",
                "elements": [
                    {
                        "type": "rich_text_section",
                        "elements": [
                            {
                                "type": "text",
                                "text": "that sounds like a great idea"
                            }
                        ]
                    }
                ]
            }
        ],
        "team": "T010YRDV4KB",
        "user_team": "T010YRDV4KB",
        "source_team": "T010YRDV4KB",
        "user_profile": {
            "avatar_hash": "2340daecb5c9",
            "image_72": "https:\/\/avatars.slack-edge.com\/2020-10-14\/1429586810659_2340daecb5c97157acec_72.png",
            "first_name": "Derek",
            "real_name": "Derek Nguyen",
            "display_name": "Derek Nguyen",
            "team": "T010YRDV4KB",
            "name": "derek.nguyen1028",
            "is_restricted": false,
            "is_ultra_restricted": false
        }
    },
    {
        "client_msg_id": "19b94dc4-010d-46ec-869b-866acf91459b",
        "type": "message",
        "text": "tbh there's not really an organized way that it's distributed, people just take lmao",
        "user": "U022WGTQ602",
        "ts": "1651726003.485599",
        "blocks": [
            {
                "type": "rich_text",
                "block_id": "fk6P",
                "elements": [
                    {
                        "type": "rich_text_section",
                        "elements": [
                            {
                                "type": "text",
                                "text": "tbh there's not really an organized way that it's distributed, people just take lmao"
                            }
                        ]
                    }
                ]
            }
        ],
        "team": "T010YRDV4KB",
        "user_team": "T010YRDV4KB",
        "source_team": "T010YRDV4KB",
        "user_profile": {
            "avatar_hash": "747c846ded5f",
            "image_72": "https:\/\/avatars.slack-edge.com\/2021-05-24\/2098572895346_747c846ded5f6d63f228_72.png",
            "first_name": "",
            "real_name": "Camden Harris",
            "display_name": "Camden Harris",
            "team": "T010YRDV4KB",
            "name": "cam.har000",
            "is_restricted": false,
            "is_ultra_restricted": false
        },
        "thread_ts": "1651725967.185999",
        "parent_user_id": "U0118UR0J72"
    }
]