[
    {
        "client_msg_id": "5285C6D8-4945-4C3F-A7C4-69DF6036FE9A",
        "type": "message",
        "text": "<!everyone> found out I have Covid",
        "user": "U02ENRPMDCZ",
        "ts": "1653095256.987009",
        "blocks": [
            {
                "type": "rich_text",
                "block_id": "TMN3",
                "elements": [
                    {
                        "type": "rich_text_section",
                        "elements": [
                            {
                                "type": "broadcast",
                                "range": "everyone"
                            },
                            {
                                "type": "text",
                                "text": " found out I have Covid"
                            }
                        ]
                    }
                ]
            }
        ],
        "team": "T010YRDV4KB",
        "user_team": "T010YRDV4KB",
        "source_team": "T010YRDV4KB",
        "user_profile": {
            "avatar_hash": "17b66d5a2701",
            "image_72": "https:\/\/avatars.slack-edge.com\/2021-09-13\/2483249218853_17b66d5a270198b7755b_72.jpg",
            "first_name": "Vincent",
            "real_name": "Vincent Luc",
            "display_name": "",
            "team": "T010YRDV4KB",
            "name": "samuraivincent10",
            "is_restricted": false,
            "is_ultra_restricted": false
        }
    },
    {
        "client_msg_id": "9E1DA949-DCCD-41DC-8EC0-86E32A711CC5",
        "type": "message",
        "text": "I've talked to a lot of y'all since Wednesday ",
        "user": "U02ENRPMDCZ",
        "ts": "1653095329.963239",
        "blocks": [
            {
                "type": "rich_text",
                "block_id": "jxn",
                "elements": [
                    {
                        "type": "rich_text_section",
                        "elements": [
                            {
                                "type": "text",
                                "text": "I've talked to a lot of y'all since Wednesday "
                            }
                        ]
                    }
                ]
            }
        ],
        "team": "T010YRDV4KB",
        "user_team": "T010YRDV4KB",
        "source_team": "T010YRDV4KB",
        "user_profile": {
            "avatar_hash": "17b66d5a2701",
            "image_72": "https:\/\/avatars.slack-edge.com\/2021-09-13\/2483249218853_17b66d5a270198b7755b_72.jpg",
            "first_name": "Vincent",
            "real_name": "Vincent Luc",
            "display_name": "",
            "team": "T010YRDV4KB",
            "name": "samuraivincent10",
            "is_restricted": false,
            "is_ultra_restricted": false
        }
    },
    {
        "client_msg_id": "b5521513-dd80-4cf2-ade2-cc6462e35a47",
        "type": "message",
        "text": "...",
        "user": "U02DWDDVAP7",
        "ts": "1653102552.122809",
        "blocks": [
            {
                "type": "rich_text",
                "block_id": "v7i",
                "elements": [
                    {
                        "type": "rich_text_section",
                        "elements": [
                            {
                                "type": "text",
                                "text": "..."
                            }
                        ]
                    }
                ]
            }
        ],
        "team": "T010YRDV4KB",
        "user_team": "T010YRDV4KB",
        "source_team": "T010YRDV4KB",
        "user_profile": {
            "avatar_hash": "1345d69f0915",
            "image_72": "https:\/\/avatars.slack-edge.com\/2022-10-25\/4285249398001_1345d69f0915bbc92727_72.png",
            "first_name": "Conner",
            "real_name": "Conner Brunner",
            "display_name": "Conner Brunner",
            "team": "T010YRDV4KB",
            "name": "con-bru000",
            "is_restricted": false,
            "is_ultra_restricted": false
        }
    },
    {
        "client_msg_id": "95abb625-4fd6-4b4c-acc6-e2234bfecc13",
        "type": "message",
        "text": "thats fun",
        "user": "U02DWDDVAP7",
        "ts": "1653102561.308019",
        "blocks": [
            {
                "type": "rich_text",
                "block_id": "yUR8",
                "elements": [
                    {
                        "type": "rich_text_section",
                        "elements": [
                            {
                                "type": "text",
                                "text": "thats fun"
                            }
                        ]
                    }
                ]
            }
        ],
        "team": "T010YRDV4KB",
        "user_team": "T010YRDV4KB",
        "source_team": "T010YRDV4KB",
        "user_profile": {
            "avatar_hash": "1345d69f0915",
            "image_72": "https:\/\/avatars.slack-edge.com\/2022-10-25\/4285249398001_1345d69f0915bbc92727_72.png",
            "first_name": "Conner",
            "real_name": "Conner Brunner",
            "display_name": "Conner Brunner",
            "team": "T010YRDV4KB",
            "name": "con-bru000",
            "is_restricted": false,
            "is_ultra_restricted": false
        }
    },
    {
        "client_msg_id": "8798b974-6214-4dd8-8352-31095e947d02",
        "type": "message",
        "text": "Good luck hope you feel better soon",
        "user": "U02DWDDVAP7",
        "ts": "1653102580.642629",
        "blocks": [
            {
                "type": "rich_text",
                "block_id": "UJZI",
                "elements": [
                    {
                        "type": "rich_text_section",
                        "elements": [
                            {
                                "type": "text",
                                "text": "Good luck hope you feel better soon"
                            }
                        ]
                    }
                ]
            }
        ],
        "team": "T010YRDV4KB",
        "user_team": "T010YRDV4KB",
        "source_team": "T010YRDV4KB",
        "user_profile": {
            "avatar_hash": "1345d69f0915",
            "image_72": "https:\/\/avatars.slack-edge.com\/2022-10-25\/4285249398001_1345d69f0915bbc92727_72.png",
            "first_name": "Conner",
            "real_name": "Conner Brunner",
            "display_name": "Conner Brunner",
            "team": "T010YRDV4KB",
            "name": "con-bru000",
            "is_restricted": false,
            "is_ultra_restricted": false
        }
    }
]